LICENSE
MANIFEST.in
README.md
setup.py
CodeHarvester.egg-info/PKG-INFO
CodeHarvester.egg-info/SOURCES.txt
CodeHarvester.egg-info/dependency_links.txt
CodeHarvester.egg-info/top_level.txt
src/harvester.py
src/codeharvester/__init__.py
src/codeharvester/harvester.py