Metadata-Version: 1.1
Name: CodeHarvester
Version: 0.0.2
Summary: A tool to merge an input file and all of its requirements into a single output file. Similar to Sprockets.
Home-page: http://packages.python.org/codeharvester
Author: Denis Gonsiorovsky
Author-email: dns.gnsr@gmail.com
License: BSD
Keywords: python js sprockets requirements dependencies merge join
Platform: UNKNOWN
Classifier: Development Status :: 3 - Alpha
Classifier: Environment :: Console
Classifier: License :: OSI Approved :: MIT License
Classifier: Operating System :: OS Independent
Classifier: Programming Language :: Python
Classifier: Programming Language :: Python :: 2
Classifier: Programming Language :: Python :: 3
Classifier: Topic :: Software Development :: Build Tools
Classifier: Topic :: Software Development :: Code Generators
Classifier: Topic :: Software Development :: Pre-processors
Classifier: Topic :: Utilities
